__init__.py
securitycopilot/__init__.py
securitycopilot/_model.py
securitycopilot/api.py
securitycopilot-0.3.0.dist-info/LICENSE
securitycopilot-0.3.0.dist-info/METADATA
securitycopilot-0.3.0.dist-info/WHEEL
securitycopilot-0.3.0.dist-info/top_level.txt
securitycopilot-0.3.0.dist-info/RECORD
