Metadata-Version: 2.1
Name: securitycopilot
Version: 0.3.0
Summary: securitycopilot
Author-email: Mark Kendrick <aeetos@gmail.com>
Classifier: Programming Language :: Python :: 3
Classifier: License :: OSI Approved :: MIT License
Classifier: Operating System :: OS Independent
Requires-Python: >=3.7
License-File: LICENSE
Requires-Dist: azure-identity
